vytal/Inter.ttf
vytal/__init__.py
vytal/adtech.py
vytal/adtech_old.py
vytal/background.png
vytal/client.py
vytal/client_old.py
vytal/client_temp.py
vytal/cogsci.py
vytal/hci.py
vytal/test.py
vytal-0.1.22.data/data/vytal/config/config.json
vytalgaze-client/__init__.py
vytalgaze-client/client.py
vytal-0.1.22.dist-info/LICENSE
vytal-0.1.22.dist-info/METADATA
vytal-0.1.22.dist-info/WHEEL
vytal-0.1.22.dist-info/top_level.txt
vytal-0.1.22.dist-info/RECORD
