Metadata-Version: 2.1
Name: vytal
Version: 0.1.22
Summary: Client for Vytal Gaze API.
Home-page: https://github.com/vytal-ai/vytal
Author: Vytal.ai
Author-email: sritanmotati@gmail.com
License: MIT
Keywords: starter,package,template
Classifier: Development Status :: 3 - Alpha
Classifier: License :: OSI Approved :: MIT License
Classifier: Natural Language :: English
Classifier: Operating System :: OS Independent
Classifier: Programming Language :: Python
Classifier: Programming Language :: Python :: 3
Classifier: Programming Language :: Python :: 3 :: Only
Classifier: Programming Language :: Python :: 3.8
Classifier: Programming Language :: Python :: 3.9
Classifier: Programming Language :: Python :: 3.10
Classifier: Programming Language :: Python :: 3.11
Classifier: Intended Audience :: Developers
Classifier: Intended Audience :: Science/Research
Classifier: Intended Audience :: Information Technology
Classifier: Topic :: Software Development
Classifier: Topic :: Software Development :: Libraries
Requires-Python: >=3.8
License-File: LICENSE
Requires-Dist: requests >=2.18.0
Requires-Dist: numpy <=1.24.0,>=1.23.0
Requires-Dist: torch >=1.0.0
Requires-Dist: websockets
Requires-Dist: opencv-python
Requires-Dist: matplotlib
Requires-Dist: PyQt5
Requires-Dist: scipy
